evedom/__init__.py
evedom/endpoint.py
evedom/loader.py
evedom/helpers/__init__.py
evedom/helpers/encoders.py
evedom-0.0.1.dist-info/DESCRIPTION.rst
evedom-0.0.1.dist-info/METADATA
evedom-0.0.1.dist-info/RECORD
evedom-0.0.1.dist-info/WHEEL
evedom-0.0.1.dist-info/metadata.json
evedom-0.0.1.dist-info/top_level.txt
